MANIFEST.in
README.rst
setup.cfg
setup.py
codedeploy_generator/__init__.py
codedeploy_generator/cli.py
codedeploy_generator.egg-info/PKG-INFO
codedeploy_generator.egg-info/SOURCES.txt
codedeploy_generator.egg-info/dependency_links.txt
codedeploy_generator.egg-info/entry_points.txt
codedeploy_generator.egg-info/requires.txt
codedeploy_generator.egg-info/top_level.txt
codedeploy_generator/commands/__init__.py
codedeploy_generator/commands/__init__.pyc
codedeploy_generator/commands/base.py
codedeploy_generator/commands/base.pyc
codedeploy_generator/commands/create.py
codedeploy_generator/commands/create.pyc
codedeploy_generator/extra/fabfile.py
codedeploy_generator/extra/package.json
codedeploy_generator/extra/requirements.txt