Metadata-Version: 1.1
Name: codedeploy-generator
Version: 1.0.16
Summary: generate deployment scripts for code_deploy
Home-page: https://github.com/bjtox/deployment-scripts-creator
Author: Antonio Bitonti
Author-email: antonio.bitonti@gmail.com
License: MIT
Keywords: aws code_deploy deployments
Platform: UNKNOWN
Classifier: Development Status :: 3 - Alpha
Classifier: License :: OSI Approved :: MIT License
Classifier: Programming Language :: Python :: 2.7
Classifier: Programming Language :: Python :: 3
Classifier: Programming Language :: Python :: 3.3
Classifier: Programming Language :: Python :: 3.4
Classifier: Programming Language :: Python :: 3.5
